Metadata-Version: 1.1
Name: swabbie
Version: 0.1.4
Summary: Helps manage your docker environment
Home-page: https://github.com/cgallag/swabbie
Author: Caroline Gallagher
Author-email: caroline@rokoid.com
License: MIT
Keywords: docker,clean,nuke,dangling images
Platform: UNKNOWN
Classifier: Development Status :: 2 - Pre-Alpha
Classifier: Intended Audience :: Developers
Classifier: License :: OSI Approved :: MIT License
